monitorable/Executable.py
monitorable/__init__.py
monitorable/encase.py
monitorable/mark.py
monitorable/utils.py
monitorable/value.py
monitorable-0.0.1.dist-info/DESCRIPTION.rst
monitorable-0.0.1.dist-info/METADATA
monitorable-0.0.1.dist-info/RECORD
monitorable-0.0.1.dist-info/WHEEL
monitorable-0.0.1.dist-info/metadata.json
monitorable-0.0.1.dist-info/top_level.txt
