Metadata-Version: 1.0
Name: monitorable
Version: 0.0.1
Summary: monitorable
Home-page: https://github.com/fierflame/monitorable.py
Author: Fierflame
Author-email: UNKNOWN
License: MIT Licence
Keywords: monitorable
Platform: any
